{"cameraMode":{"drawMode":0,"name":"Shaded","section":"Shading Mode"},"sceneLighting":false,"audioPlay":false,"sceneViewState":{"m_AlwaysRefresh":false,"showFog":true,"showSkybox":false,"showFlares":true,"showImageEffects":true,"showParticleSystems":true,"showVisualEffectGraphs":true,"m_FxEnabled":true},"in2DMode":false,"pivot":{"x":0.0037755966186523439,"y":0.36635351181030276,"z":-0.010850489139556885},"rotation":{"x":0.05171962454915047,"y":-0.804397463798523,"z":0.0713343620300293,"w":0.5880222320556641},"size":0.46988046169281008,"orthographic":false}